geodatafusion-0.1.1.dist-info/METADATA
geodatafusion-0.1.1.dist-info/WHEEL
geodatafusion/__init__.py
geodatafusion/_rust.pyi
geodatafusion/_rust.pypy310-pp73-aarch64-linux-gnu.so
geodatafusion/geo/__init__.pyi
geodatafusion/geo/_measurement.pyi
geodatafusion/geo/_processing.pyi
geodatafusion/geo/_relationships.pyi
geodatafusion/geo/_validation.pyi
geodatafusion/geohash.pyi
geodatafusion/native/__init__.pyi
geodatafusion/native/_accessors.pyi
geodatafusion/native/_bounding_box.pyi
geodatafusion/native/_constructors.pyi
geodatafusion/native/_io.pyi
geodatafusion/py.typed
geodatafusion-0.1.1.dist-info/RECORD
